pyuwb/KalmanFilter.py
pyuwb/__init__.py
pyuwb/anchor_locate_algorithm1.py
pyuwb/calc_crc.py
pyuwb/client_id_utils.py
pyuwb/detect_com_port.py
pyuwb/dingwei.py
pyuwb/dist_list_dict_convert.py
pyuwb/locate_base.py
pyuwb/modbus_pkt.py
pyuwb/my_short.py
pyuwb/mylog.py
pyuwb/pyuwb.py
pyuwb/pyuwb_test.py
pyuwb/tag_locate_algorithm1.py
pyuwb/uwb_modbus.py
pyuwb-0.0.8.dist-info/LICENSE
pyuwb-0.0.8.dist-info/METADATA
pyuwb-0.0.8.dist-info/WHEEL
pyuwb-0.0.8.dist-info/entry_points.txt
pyuwb-0.0.8.dist-info/top_level.txt
pyuwb-0.0.8.dist-info/RECORD
