Metadata-Version: 2.1
Name: pyuwb
Version: 0.0.8
Summary: A uwb locating library
Home-page: https://github.com/Jiangshan00001/pyuwb
Author: jiangshan00000
Author-email: 710806594@qq.com
License: UNKNOWN
Platform: UNKNOWN
Classifier: Programming Language :: Python :: 3
Classifier: License :: OSI Approved :: MIT License
Classifier: Operating System :: OS Independent
Requires-Dist: pyserial
